valley_free-0.2.0.dist-info/METADATA
valley_free-0.2.0.dist-info/WHEEL
valley_free/__init__.py
valley_free/valley_free.cpython-39-x86_64-linux-gnu.so
valley_free-0.2.0.dist-info/RECORD
