Metadata-Version: 2.1
Name: valley-free
Version: 0.2.0
Summary: BGP valley-free routing AS path exploration library
Keywords: bgp,valley-free,network,simulation
Author: Mingwei Zhang <mingwei@bgpkit.com>
Author-email: Mingwei Zhang <mingwei@bgpkit.com>
License: MIT
Project-URL: Source Code, https://github.com/bgpkit/valley-free
